corpus_similarity/__init__.py
corpus_similarity/corpus_similarity.py
corpus_similarity/in_domain_features/!ReadMe.txt
corpus_similarity/in_domain_features/!ReadMe_Pacific.txt
corpus_similarity/in_domain_features/__init__.py
corpus_similarity/in_domain_features/amh_5k_IN_char4.json
corpus_similarity/in_domain_features/ara_5k_IN_word1.json
corpus_similarity/in_domain_features/aze_5k_IN_char4.json
corpus_similarity/in_domain_features/ben_5k_IN_char4.json
corpus_similarity/in_domain_features/bul_5k_IN_char4.json
corpus_similarity/in_domain_features/cat_5k_IN_char4.json
corpus_similarity/in_domain_features/ceb_5k_IN_char4.json
corpus_similarity/in_domain_features/ces_5k_IN_char4.json
corpus_similarity/in_domain_features/cha_5k_IN_char4.json
corpus_similarity/in_domain_features/dan_5k_IN_char4.json
corpus_similarity/in_domain_features/deu_5k_IN_char4.json
corpus_similarity/in_domain_features/ell_5k_IN_char4.json
corpus_similarity/in_domain_features/eng_5k_IN_char4.json
corpus_similarity/in_domain_features/est_5k_IN_word1.json
corpus_similarity/in_domain_features/eus_5k_IN_word1.json
corpus_similarity/in_domain_features/fas_5k_IN_char3.json
corpus_similarity/in_domain_features/fij_5k_IN_char4.json
corpus_similarity/in_domain_features/fin_5k_IN_char4.json
corpus_similarity/in_domain_features/fra_5k_IN_word1.json
corpus_similarity/in_domain_features/gle_5k_IN_word1.json
corpus_similarity/in_domain_features/glg_5k_IN_char4.json
corpus_similarity/in_domain_features/guj_5k_IN_char4.json
corpus_similarity/in_domain_features/hat_5k_IN_char4.json
corpus_similarity/in_domain_features/haw_5k_IN_char4.json
corpus_similarity/in_domain_features/heb_5k_IN_char4.json
corpus_similarity/in_domain_features/hin_5k_IN_char4.json
corpus_similarity/in_domain_features/hmo_5k_IN_char4.json
corpus_similarity/in_domain_features/hun_5k_IN_char4.json
corpus_similarity/in_domain_features/ilo_5k_IN_char4.json
corpus_similarity/in_domain_features/ind_5k_IN_word1.json
corpus_similarity-1.1.dist-info/LICENSE
corpus_similarity-1.1.dist-info/METADATA
corpus_similarity-1.1.dist-info/WHEEL
corpus_similarity-1.1.dist-info/top_level.txt
corpus_similarity-1.1.dist-info/RECORD
