Metadata-Version: 2.1
Name: corpus-similarity
Version: 1.1
Summary: Measuring corpus similarity in Python
Home-page: https://github.com/jonathandunn/corpus_similarity
Author: Jonathan Dunn, Haipeng Li, Damian Sastre
Author-email: jonathan.dunn@canterbury.ac.nz
License: GNU GENERAL PUBLIC LICENSE v3
Keywords: text analytics,natural language processing,computational linguistics,corpus,corpora,similarity
Platform: UNKNOWN
License-File: LICENSE
Requires-Dist: cytoolz
Requires-Dist: numpy
Requires-Dist: clean-text
Requires-Dist: scipy
Requires-Dist: scikit-learn
